xcsp/__init__.py
xcsp/main.py
xcsp/builder/__init__.py
xcsp/builder/build.py
xcsp/builder/check.py
xcsp/commands/__init__.py
xcsp/commands/install.py
xcsp/commands/solver.py
xcsp/solver/__init__.py
xcsp/solver/cache.py
xcsp/solver/resolver.py
xcsp/solver/solver.py
xcsp/utils/__init__.py
xcsp/utils/archive.py
xcsp/utils/args.py
xcsp/utils/bootstrap.py
xcsp/utils/dict.py
xcsp/utils/http.py
xcsp/utils/json.py
xcsp/utils/log.py
xcsp/utils/paths.py
xcsp/utils/placeholder.py
xcsp/utils/softwarevers.py
xcsp/utils/system.py
xcsp/utils/versiondir/__init__.py
xcsp/utils/versiondir/backend.py
xcsp/utils/versiondir/core.py
xcsp-0.7.0.dist-info/licenses/LICENSE.md
xcsp-0.7.0.dist-info/METADATA
xcsp-0.7.0.dist-info/WHEEL
xcsp-0.7.0.dist-info/entry_points.txt
xcsp-0.7.0.dist-info/top_level.txt
xcsp-0.7.0.dist-info/RECORD
