Metadata-Version: 2.4
Name: xcsp
Version: 0.7.0
Summary: A unified launcher for XCSP solver
Author-email: Thibault Falque <contact@tootatis.dev>, Romain Wallon <contact@tootatis.dev>
License-Expression: LGPL-3.0-or-later
Project-URL: Homepage, https://tootatis.dev
Project-URL: Documentation, https://xcsp.readthedocs.org
Project-URL: Repository, https://github.com/CPToolset/xcsp-launcher
Project-URL: Issues, https://github.com/CPToolset/xcsp-launcher/issues
Project-URL: Changelog, https://github.com/CPToolset/xcsp-launcher/blob/main/CHANGELOG.md
Keywords: XCSP,solver,constraint-programming,launcher
Classifier: Development Status :: 3 - Alpha
Classifier: Programming Language :: Python :: 3 :: Only
Classifier: Programming Language :: Python :: 3.10
Classifier: Programming Language :: Python :: 3.11
Classifier: Programming Language :: Python :: 3.12
Classifier: Programming Language :: Python :: 3.13
Classifier: Operating System :: OS Independent
Requires-Python: >=3.10
License-File: LICENSE.md
Requires-Dist: loguru
Requires-Dist: tqdm
Requires-Dist: platformdirs
Requires-Dist: pyfiglet
Requires-Dist: GitPython
Requires-Dist: PyYAML
Requires-Dist: psutil
Requires-Dist: rich
Provides-Extra: test
Requires-Dist: pytest; extra == "test"
Requires-Dist: pytest-xdist; extra == "test"
Provides-Extra: docs
Requires-Dist: sphinx>=5.3.0; extra == "docs"
Requires-Dist: sphinx_rtd_theme>=2.0.0; extra == "docs"
Requires-Dist: myst_parser; extra == "docs"
Requires-Dist: sphinx-automodapi; extra == "docs"
Requires-Dist: readthedocs-sphinx-search>=0.3.2; extra == "docs"
Dynamic: license-file
